opustools/__init__.py
opustools/db_operations.py
opustools/formatting.py
opustools/opus_cat.py
opustools/opus_file_handler.py
opustools/opus_get.py
opustools/opus_langid.py
opustools/opus_read.py
opustools/opusdata.db.gz
opustools/readopusdata.py
opustools/util.py
opustools/parse/__init__.py
opustools/parse/alignment_parser.py
opustools/parse/block_parser.py
opustools/parse/sentence_parser.py
opustools-1.8.2.data/scripts/opus_cat
opustools-1.8.2.data/scripts/opus_express
opustools-1.8.2.data/scripts/opus_get
opustools-1.8.2.data/scripts/opus_langid
opustools-1.8.2.data/scripts/opus_read
opustools-1.8.2.dist-info/licenses/LICENSE
tests/__init__.py
tests/test_alignment_parser.py
tests/test_block_parser.py
tests/test_db_operations.py
tests/test_opus_cat.py
tests/test_opus_get.py
tests/test_opus_langid.py
tests/test_opus_read.py
tests/test_sentence_parser.py
opustools-1.8.2.dist-info/METADATA
opustools-1.8.2.dist-info/WHEEL
opustools-1.8.2.dist-info/top_level.txt
opustools-1.8.2.dist-info/RECORD
