Metadata-Version: 2.4
Name: opustools
Version: 1.8.2
Summary: Tools to read OPUS
Home-page: https://github.com/Helsinki-NLP/OpusTools
Author: Mikko Aulamo
Author-email: mikko.aulamo@helsinki.fi
Classifier: Programming Language :: Python :: 3
Classifier: License :: OSI Approved :: MIT License
Classifier: Operating System :: OS Independent
License-File: LICENSE
Requires-Dist: ruamel.yaml
Provides-Extra: langid
Requires-Dist: pycld2; extra == "langid"
Requires-Dist: langid; extra == "langid"
Provides-Extra: all
Requires-Dist: pycld2; extra == "all"
Requires-Dist: langid; extra == "all"
Dynamic: author
Dynamic: author-email
Dynamic: classifier
Dynamic: description
Dynamic: description-content-type
Dynamic: home-page
Dynamic: license-file
Dynamic: provides-extra
Dynamic: requires-dist
Dynamic: summary
